aliyunsdkimgsearch/__init__.py
aliyunsdkimgsearch/endpoint.py
aliyunsdkimgsearch/request/__init__.py
aliyunsdkimgsearch/request/v20200320/AddImageRequest.py
aliyunsdkimgsearch/request/v20200320/CreateImageDbRequest.py
aliyunsdkimgsearch/request/v20200320/DeleteImageDbRequest.py
aliyunsdkimgsearch/request/v20200320/DeleteImageRequest.py
aliyunsdkimgsearch/request/v20200320/ListImageDbsRequest.py
aliyunsdkimgsearch/request/v20200320/ListImagesRequest.py
aliyunsdkimgsearch/request/v20200320/SearchImageRequest.py
aliyunsdkimgsearch/request/v20200320/__init__.py
aliyun_python_sdk_imgsearch-1.1.7.dist-info/LICENSE
aliyun_python_sdk_imgsearch-1.1.7.dist-info/METADATA
aliyun_python_sdk_imgsearch-1.1.7.dist-info/WHEEL
aliyun_python_sdk_imgsearch-1.1.7.dist-info/top_level.txt
aliyun_python_sdk_imgsearch-1.1.7.dist-info/RECORD
